sio3pack/__init__.py
sio3pack/util.py
sio3pack/django/__init__.py
sio3pack/django/common/__init__.py
sio3pack/django/common/handler.py
sio3pack/django/common/models.py
sio3pack/django/common/migrations/0001_initial.py
sio3pack/django/common/migrations/0002_alter_sio3packmodelsolution_package_and_more.py
sio3pack/django/common/migrations/0003_alter_sio3packnametranslation_language_and_more.py
sio3pack/django/common/migrations/0004_sio3packtest_sio3packmainmodelsolution.py
sio3pack/django/common/migrations/0005_alter_sio3packtest_options_and_more.py
sio3pack/django/common/migrations/0006_alter_sio3packmainmodelsolution_package_and_more.py
sio3pack/django/common/migrations/__init__.py
sio3pack/django/sinolpack/__init__.py
sio3pack/django/sinolpack/handler.py
sio3pack/django/sinolpack/models.py
sio3pack/django/sinolpack/migrations/0001_initial.py
sio3pack/django/sinolpack/migrations/0002_alter_sinolpackadditionalfile_package_and_more.py
sio3pack/django/sinolpack/migrations/0003_sinolpackspecialfile.py
sio3pack/django/sinolpack/migrations/0004_sinolpackextrafile.py
sio3pack/django/sinolpack/migrations/__init__.py
sio3pack/exceptions/__init__.py
sio3pack/exceptions/general.py
sio3pack/exceptions/packages.py
sio3pack/exceptions/workflow.py
sio3pack/files/__init__.py
sio3pack/files/file.py
sio3pack/files/local_file.py
sio3pack/files/remote_file.py
sio3pack/lua/__init__.py
sio3pack/packages/__init__.py
sio3pack/packages/package/__init__.py
sio3pack/packages/package/configuration.py
sio3pack/packages/package/handler.py
sio3pack/packages/package/model.py
sio3pack/packages/sinolpack/__init__.py
sio3pack/packages/sinolpack/constants.py
sio3pack/packages/sinolpack/enums.py
sio3pack/packages/sinolpack/model.py
sio3pack/packages/sinolpack/workflows.py
sio3pack/test/__init__.py
sio3pack/test/test.py
sio3pack/utils/__init__.py
sio3pack/utils/archive.py
sio3pack/utils/classinit.py
sio3pack/visualizer/__init__.py
sio3pack/visualizer/cytoscope.py
sio3pack/workflow/__init__.py
sio3pack-1.0.0.dev5.dist-info/licenses/LICENSE
sio3pack-1.0.0.dev5.dist-info/METADATA
sio3pack-1.0.0.dev5.dist-info/WHEEL
sio3pack-1.0.0.dev5.dist-info/entry_points.txt
sio3pack-1.0.0.dev5.dist-info/top_level.txt
sio3pack-1.0.0.dev5.dist-info/RECORD
